feature_gates/__init__.py
pyteal/__init__.py
pyteal/__init__.pyi
pyteal/config.py
pyteal/errors.py
pyteal/py.typed
pyteal/stack_frame.py
pyteal/stack_frame_test.py
pyteal/types.py
pyteal/types_test.py
pyteal/util.py
pyteal/ast/__init__.py
pyteal/ast/abstractvar.py
pyteal/ast/acct.py
pyteal/ast/acct_test.py
pyteal/ast/addr.py
pyteal/ast/addr_test.py
pyteal/ast/app.py
pyteal/ast/app_test.py
pyteal/ast/arg.py
pyteal/ast/arg_test.py
pyteal/ast/array.py
pyteal/ast/assert_.py
pyteal/ast/assert_test.py
pyteal/ast/asset.py
pyteal/ast/asset_test.py
pyteal/ast/base64decode.py
pyteal/ast/base64decode_test.py
pyteal/ast/binaryexpr.py
pyteal/ast/binaryexpr_test.py
pyteal/ast/block.py
pyteal/ast/block_test.py
pyteal/ast/box.py
pyteal/ast/box_test.py
pyteal/ast/break_.py
pyteal/ast/break_test.py
pyteal/ast/bytes.py
pyteal/ast/bytes_test.py
pyteal/ast/comment.py
pyteal/ast/comment_test.py
pyteal/ast/cond.py
pyteal/ast/cond_test.py
pyteal/ast/continue_.py
pyteal/ast/continue_test.py
pyteal/ast/ec.py
pyteal/ast/ec_test.py
pyteal/ast/ecdsa.py
pyteal/ast/ecdsa_test.py
pyteal/ast/err.py
pyteal/ast/err_test.py
pyteal/ast/expr.py
pyteal/ast/for_.py
pyteal/ast/for_test.py
pyteal/ast/frame.py
pyteal/ast/frame_test.py
pyteal/ast/gaid.py
pyteal/ast/gaid_test.py
pyteal/ast/gitxn.py
pyteal/ast/gitxn_test.py
pyteal/ast/gload.py
pyteal/ast/gload_test.py
pyteal/ast/global_.py
pyteal/ast/global_test.py
pyteal/ast/gtxn.py
pyteal/ast/gtxn_test.py
pyteal/ast/if_.py
pyteal/ast/if_test.py
pyteal/ast/int.py
pyteal/ast/int_test.py
pyteal/ast/itxn.py
pyteal/ast/itxn_test.py
pyteal/ast/jsonref.py
pyteal/ast/jsonref_test.py
pyteal/ast/leafexpr.py
pyteal/ast/maybe.py
pyteal/ast/maybe_test.py
pyteal/ast/methodsig.py
pyteal/ast/methodsig_test.py
pyteal/ast/mimc.py
pyteal/ast/mimc_test.py
pyteal/ast/multi.py
pyteal/ast/multi_test.py
pyteal/ast/naryexpr.py
pyteal/ast/naryexpr_test.py
pyteal/ast/nonce.py
pyteal/ast/nonce_test.py
pyteal/ast/opup.py
pyteal/ast/opup_test.py
pyteal/ast/pragma.py
pyteal-0.27.0.dist-info/LICENSE
pyteal-0.27.0.dist-info/METADATA
pyteal-0.27.0.dist-info/WHEEL
pyteal-0.27.0.dist-info/top_level.txt
pyteal-0.27.0.dist-info/RECORD
