Metadata-Version: 2.1
Name: pyteal
Version: 0.27.0
Summary: Algorand Smart Contracts in Python
Home-page: https://github.com/algorand/pyteal
Author: Algorand
Author-email: pypiservice@algorand.com
Classifier: Programming Language :: Python :: 3
Classifier: License :: OSI Approved :: MIT License
Classifier: Operating System :: OS Independent
Requires-Python: >=3.10
License-File: LICENSE
